simplemoer/__init__.py
simplemoer/client.py
simplemoer/example.env
simplemoer/example.py
simplemoer/example_register.py
simplemoer-0.0.4.dist-info/METADATA
simplemoer-0.0.4.dist-info/WHEEL
simplemoer-0.0.4.dist-info/licenses/LICENSE
simplemoer-0.0.4.dist-info/RECORD
