Metadata-Version: 2.1
Name: simplemoer
Version: 0.0.4
Summary: Python client for the WattTime API
Project-URL: Homepage, https://github.com/kylehodgson/simplemoer
Project-URL: Bug Tracker, https://github.com/kylehodgson/simplemoer/issues
Author-email: Kyle Hodgson <kyle.hodgson@gmail.com>
License-File: LICENSE
Classifier: License :: OSI Approved :: MIT License
Classifier: Operating System :: OS Independent
Classifier: Programming Language :: Python :: 3
Requires-Python: >=3.7
Requires-Dist: requests<3,>=2.20.0
